reds_simple_logger/__init__.py
reds_simple_logger-2.4.dist-info/METADATA
reds_simple_logger-2.4.dist-info/WHEEL
reds_simple_logger-2.4.dist-info/top_level.txt
reds_simple_logger-2.4.dist-info/RECORD
