Metadata-Version: 2.1
Name: reds_simple_logger
Version: 2.4
Summary: Allows you to make console logging more simple.
Author: Red_Wolf2467
Author-email: support@pyropixle.com
Requires-Python: >=3.8
Requires-Dist: termcolor
Requires-Dist: datetime
